tests/__init__.py
tests/test_package.py
ukbb_py/Power_Calculations.py
ukbb_py/UKBB_Health_Records_New_Project.py
ukbb_py/__init__.py
ukbb_py/extract_sql_data.py
ukbb_py-0.1.0.dist-info/LICENSE.txt
ukbb_py-0.1.0.dist-info/METADATA
ukbb_py-0.1.0.dist-info/WHEEL
ukbb_py-0.1.0.dist-info/top_level.txt
ukbb_py-0.1.0.dist-info/RECORD
