Metadata-Version: 2.1
Name: ukbb_py
Version: 0.1.0
Summary: An ensemble of functions for analysing UKBB records on DNA Nexus.
Home-page: https://github.com/Surajram112/UKBB_py
Author: Suraj Ramchand
Author-email: surajnramchand@gmail.com
Classifier: Programming Language :: Python :: 3
Classifier: Operating System :: OS Independent
Requires-Python: >=3.6
License-File: LICENSE.txt
Requires-Dist: pandas
Requires-Dist: numpy
Requires-Dist: scipy
Requires-Dist: matplotlib
Requires-Dist: seaborn
Requires-Dist: statsmodels
Requires-Dist: polars
Requires-Dist: pyarrow
Requires-Dist: fastparquet
